jstudio/__init__.py
jstudio/client.py
jstudio-1.0.0.dist-info/licenses/LICENSE
jstudio-1.0.0.dist-info/METADATA
jstudio-1.0.0.dist-info/WHEEL
jstudio-1.0.0.dist-info/top_level.txt
jstudio-1.0.0.dist-info/RECORD
