Metadata-Version: 2.4
Name: jstudio
Version: 1.0.0
Summary: Official Python SDK for JStudio's API & WebSocket services - Fast, reliable API for real-time data from Various Games (Roblox)
Home-page: https://github.com/JStudiooo/growagarden-api
Author: JStudio
Author-email: contact@joshlei.com
Project-URL: Bug Tracker, https://discord.gg/kCryJ8zPwy
Project-URL: Homepage, https://api.joshlei.com
Keywords: jstudio,grow-a-garden,roblox,api,sdk,gaming,real-time
Classifier: Development Status :: 5 - Production/Stable
Classifier: Intended Audience :: Developers
Classifier: License :: OSI Approved :: MIT License
Classifier: Operating System :: OS Independent
Classifier: Programming Language :: Python :: 3
Classifier: Programming Language :: Python :: 3.7
Classifier: Programming Language :: Python :: 3.8
Classifier: Programming Language :: Python :: 3.9
Classifier: Programming Language :: Python :: 3.10
Classifier: Programming Language :: Python :: 3.11
Classifier: Programming Language :: Python :: 3.12
Classifier: Topic :: Internet :: WWW/HTTP
Classifier: Topic :: Software Development :: Libraries :: Python Modules
Classifier: Topic :: Games/Entertainment
Requires-Python: >=3.7
License-File: LICENSE
Requires-Dist: requests>=2.25.0
Dynamic: author
Dynamic: author-email
Dynamic: classifier
Dynamic: description
Dynamic: description-content-type
Dynamic: home-page
Dynamic: keywords
Dynamic: license-file
Dynamic: project-url
Dynamic: requires-dist
Dynamic: requires-python
Dynamic: summary
